benchmarks/locustfile.py
fastserve/__init__.py
fastserve/__main__.py
fastserve/batching.py
fastserve/core.py
fastserve/handler.py
fastserve/middleware.py
fastserve/utils.py
fastserve/client/__init__.py
fastserve/client/vllm.py
fastserve/deploy/__init__.py
fastserve/deploy/lightning.py
fastserve/models/__init__.py
fastserve/models/__main__.py
fastserve/models/face_reco.py
fastserve/models/image_classification.py
fastserve/models/llama_cpp.py
fastserve/models/sdxl_turbo.py
fastserve/models/ssd.py
fastserve/models/vllm.py
ui/dist/index.html
ui/dist/vite.svg
ui/dist/assets/index-6-S8NhO-.css
ui/dist/assets/index-BWQ9B7__.js
ui/dist/assets/sdxl-turbo-DtBCg58l.jpeg
FastServeAI-0.0.3.dist-info/LICENSE
FastServeAI-0.0.3.dist-info/METADATA
FastServeAI-0.0.3.dist-info/WHEEL
FastServeAI-0.0.3.dist-info/top_level.txt
FastServeAI-0.0.3.dist-info/RECORD
