Metadata-Version: 2.1
Name: FastServeAI
Version: 0.0.3
Summary: 'Machine Learning Serving focused on GenAI & LLMs with simplicity as the top priority.'
Home-page: https://github.com/aniketmaurya/fastserve
Author: Aniket Maurya
Author-email: theaniketmaurya@gmail.com
License: Apache License 2.0
Keywords: opensource,python
Requires-Python: >=3.8
License-File: LICENSE
Requires-Dist: fastapi[all]
Requires-Dist: llama-cpp-python
Requires-Dist: transformers
Requires-Dist: diffusers
Requires-Dist: uactor
